httpie_llnw_auth.py
httpie_llnw_auth-1.0.1.dist-info/LICENSE
httpie_llnw_auth-1.0.1.dist-info/METADATA
httpie_llnw_auth-1.0.1.dist-info/WHEEL
httpie_llnw_auth-1.0.1.dist-info/entry_points.txt
httpie_llnw_auth-1.0.1.dist-info/top_level.txt
httpie_llnw_auth-1.0.1.dist-info/RECORD
