Metadata-Version: 2.1
Name: httpie-llnw-auth
Version: 1.0.1
Summary: LLNW header-based auth plugin for HTTPie.
Home-page: https://github.com/llnw/httpie-llnw-auth
Author: Limelight Networks
Author-email: opensource@llnw.com
License: Apache License 2.0
Platform: UNKNOWN
Requires-Python: >=3.6
Requires-Dist: httpie (>=2.0.0)
Requires-Dist: requests-llnw-auth (>=1.0.1)
